genie.py
genie_chart.py-1.0.4.dist-info/LICENSE
genie_chart.py-1.0.4.dist-info/METADATA
genie_chart.py-1.0.4.dist-info/WHEEL
genie_chart.py-1.0.4.dist-info/top_level.txt
genie_chart.py-1.0.4.dist-info/RECORD
