Metadata-Version: 2.1
Name: genie-chart.py
Version: 1.0.4
Summary: Python API for downloading Genie charts
Home-page: https://github.com/gold24park/genie-chart.py
Author: Lou Park
Author-email: gold24park@gmail.com
License: MIT License
License-File: LICENSE
Requires-Dist: requests (>=2.28.2)
